{
  "alias_target": null,
  "collection": null,
  "documentation_status": "generated",
  "documentation_url": null,
  "guid": "{0002441b-0001-0000-c000-000000000046}",
  "id": "excel.irefreshevents",
  "implemented_interface_count": 1,
  "implemented_status": "not-started",
  "kind": "event-interface",
  "members": [
    {
      "arguments": [
        {
          "default": null,
          "direction": "in-out",
          "normalized_type": "bool",
          "optional": false,
          "position": 0,
          "raw_com_type": "VT_PTR(VT_bool (11))"
        }
      ],
      "chosen_crate_invoke_kinds": [],
      "dispid": 1596,
      "documentation_status": "generated",
      "id": "excel.irefreshevents.beforerefresh",
      "implementation_status": "not-started",
      "invoke_kinds": [
        "METHOD"
      ],
      "kind": "event",
      "member_origin": "declared",
      "microsoft_sample_invoke_kinds": [],
      "name": "BeforeRefresh",
      "notes": [],
      "optional_argument_count": 0,
      "raw_return_type": "VT_Unknown (25)",
      "return_type": "Unknown",
      "runtime_confirmed_invoke_kinds": [],
      "schema_version": 1,
      "source": {
        "microsoft_docs": false,
        "runtime_verified": false,
        "typelib": true
      },
      "source_confidence": "typelib-only",
      "test_status": "not-tested",
      "typelib_invoke_kinds": [
        "METHOD"
      ]
    },
    {
      "arguments": [
        {
          "default": null,
          "direction": "in",
          "normalized_type": "bool",
          "optional": false,
          "position": 0,
          "raw_com_type": "VT_bool (11)"
        }
      ],
      "chosen_crate_invoke_kinds": [],
      "dispid": 1597,
      "documentation_status": "generated",
      "id": "excel.irefreshevents.afterrefresh",
      "implementation_status": "not-started",
      "invoke_kinds": [
        "METHOD"
      ],
      "kind": "event",
      "member_origin": "declared",
      "microsoft_sample_invoke_kinds": [],
      "name": "AfterRefresh",
      "notes": [],
      "optional_argument_count": 0,
      "raw_return_type": "VT_Unknown (25)",
      "return_type": "Unknown",
      "runtime_confirmed_invoke_kinds": [],
      "schema_version": 1,
      "source": {
        "microsoft_docs": false,
        "runtime_verified": false,
        "typelib": true
      },
      "source_confidence": "typelib-only",
      "test_status": "not-tested",
      "typelib_invoke_kinds": [
        "METHOD"
      ]
    }
  ],
  "name": "IRefreshEvents",
  "roadmap_class": "deferred-inventory",
  "schema_version": 1,
  "source_interface": "IRefreshEvents",
  "surface_class": "event-interface",
  "test_status": "not-tested",
  "typelib_type_flags": 4112,
  "typelib_version": {
    "major": 1,
    "minor": 9
  }
}
