{
  "documentation_status": "generated",
  "guid": "{00000000-0000-0000-0000-000000000000}",
  "id": "excel.enum.xlhebrewmodes",
  "implementation_status": "not-started",
  "name": "XlHebrewModes",
  "schema_version": 1,
  "variants": [
    {
      "dispid": 1073741824,
      "documentation_status": "generated",
      "implementation_status": "not-started",
      "name": "xlHebrewFullScript",
      "numeric_value": 0
    },
    {
      "dispid": 1073741827,
      "documentation_status": "generated",
      "implementation_status": "not-started",
      "name": "xlHebrewMixedAuthorizedScript",
      "numeric_value": 3
    },
    {
      "dispid": 1073741826,
      "documentation_status": "generated",
      "implementation_status": "not-started",
      "name": "xlHebrewMixedScript",
      "numeric_value": 2
    },
    {
      "dispid": 1073741825,
      "documentation_status": "generated",
      "implementation_status": "not-started",
      "name": "xlHebrewPartialScript",
      "numeric_value": 1
    }
  ]
}
